fiscus/__init__.py
fiscus/__main__.py
fiscus/audit.py
fiscus/callbacks.py
fiscus/client.py
fiscus/client_ai_execute.py
fiscus/client_execute.py
fiscus/client_logging_config.py
fiscus/client_stream.py
fiscus/client_user_action.py
fiscus/connection.py
fiscus/connector.py
fiscus/enums.py
fiscus/exceptions.py
fiscus/fiscus_file.py
fiscus/fiscus_token.py
fiscus/orchestrator.py
fiscus/response.py
fiscus/user.py
fiscus/utility.py
fiscus-0.1.0a8.dist-info/METADATA
fiscus-0.1.0a8.dist-info/WHEEL
fiscus-0.1.0a8.dist-info/entry_points.txt
fiscus-0.1.0a8.dist-info/licenses/LICENSE
fiscus-0.1.0a8.dist-info/RECORD
